{
  "schema_version": "goalcli-mva/v1",
  "command": "goal-runtime-final",
  "status": "passed",
  "goal_id": "GOAL-20260603-XLIB-GOALCLI-001",
  "gate": "G12_G16_FINAL",
  "mode": "FULL",
  "executor": "goalcli",
  "control_plane": "Harness Runtime",
  "blocking": true,
  "mva_status": "complete",
  "ledger_path": ".agent/evidence/ledger.jsonl",
  "evidence_pack_path": "release/evidence/goalcli/GOAL-20260603-XLIB-GOALCLI-001.json",
  "gates": [
    {
      "id": "G12_ACCEPTANCE",
      "command": "goal-acceptance",
      "status": "passed",
      "blocking": true
    },
    {
      "id": "G13_DELIVERY",
      "command": "goal-delivery",
      "status": "passed",
      "blocking": true
    },
    {
      "id": "G14_HANDOVER",
      "command": "goal-handover",
      "status": "passed",
      "blocking": true
    },
    {
      "id": "G15_DOWNSTREAM_ADOPTION",
      "command": "goal-downstream-adoption",
      "status": "passed",
      "blocking": true
    },
    {
      "id": "G16_CERTIFY",
      "command": "goal-certify",
      "status": "passed",
      "blocking": true
    }
  ],
  "details": [
    "G12-G16 本地 contract 汇总为 goalcli v0.1.0 MVA final evidence",
    "goalcli v0.1.0 使用 cmd/goalcli 作为唯一执行面；不再保留历史并列入口",
    "G12-G16 是 goalcli MVA evidence gates，不是全局 release blocking gates",
    "root plan 是 authority；完成状态由本地 authority 校验和 evidence 写入共同证明",
    "downstream adoption evidence 仅声明 xlib-standard 本地 contract；不声明 proof-based downstream adoption"
  ],
  "evidence": [
    "fixture_id=GOAL-20260603-XLIB-GOALCLI-001",
    "source_evidence_ledger=.agent/evidence/ledger.jsonl",
    "generated_evidence_pack=release/evidence/goalcli/",
    "runtime_logic=internal/goalruntime",
    "adoption_claim=not_claimed",
    "downstream_adoption_scope=local_contract_only",
    "proof_based_adoption=false",
    "downstream_repo_write=false",
    "requires=goal-acceptance",
    "requires=goal-delivery",
    "requires=goal-handover",
    "requires=goal-downstream-adoption",
    "requires=goal-certify"
  ],
  "authority_paths": [
    ".worktree/goalcli-v0.1.0-plan.md",
    ".omx/context/goalcli-v0.1.0-team-20260603T005302Z.md",
    "docs/adr/ADR-20260603-001-goalcli-runtime.md",
    "docs/standard/goalcli-cli-contract.md",
    ".agent/harness.yaml",
    ".agent/command-registry.yaml",
    ".agent/registry/runtime.yaml",
    ".agent/registry/commands.yaml",
    ".agent/command-implementation-status.yaml",
    ".agent/evidence/README.md",
    "docs/standard/goalcli-runtime.md",
    "docs/plans/goalcli-v0.1.0-roadmap.md",
    "Makefile"
  ]
}
